odoo8_addon_crm_track_next_action-8.0.1.0.0.99.dev12-py3.8-nspkg.pth
odoo_addons/crm_track_next_action/README.rst
odoo_addons/crm_track_next_action/__init__.py
odoo_addons/crm_track_next_action/__openerp__.py
odoo_addons/crm_track_next_action/i18n/bg.po
odoo_addons/crm_track_next_action/i18n/crm_track_next_action.pot
odoo_addons/crm_track_next_action/i18n/de.po
odoo_addons/crm_track_next_action/i18n/es.po
odoo_addons/crm_track_next_action/i18n/fr.po
odoo_addons/crm_track_next_action/i18n/hr.po
odoo_addons/crm_track_next_action/i18n/it.po
odoo_addons/crm_track_next_action/i18n/pt_BR.po
odoo_addons/crm_track_next_action/i18n/sk.po
odoo_addons/crm_track_next_action/i18n/sl.po
odoo_addons/crm_track_next_action/i18n/zh_CN.po
odoo_addons/crm_track_next_action/models/__init__.py
odoo_addons/crm_track_next_action/models/crm_lead.py
odoo_addons/crm_track_next_action/static/description/icon.png
odoo8_addon_crm_track_next_action-8.0.1.0.0.99.dev12.dist-info/METADATA
odoo8_addon_crm_track_next_action-8.0.1.0.0.99.dev12.dist-info/WHEEL
odoo8_addon_crm_track_next_action-8.0.1.0.0.99.dev12.dist-info/namespace_packages.txt
odoo8_addon_crm_track_next_action-8.0.1.0.0.99.dev12.dist-info/top_level.txt
odoo8_addon_crm_track_next_action-8.0.1.0.0.99.dev12.dist-info/RECORD
